README
htmldiff.py
setup.py
htmldiff.egg-info/PKG-INFO
htmldiff.egg-info/SOURCES.txt
htmldiff.egg-info/dependency_links.txt
htmldiff.egg-info/not-zip-safe
htmldiff.egg-info/top_level.txt