Metadata-Version: 1.0
Name: htmldiff
Version: 0.1
Summary: Diffs arbitrary HTML inline.
Home-page: http://github.com/mitsuhiko/htmldiff
Author: Armin Ronacher
Author-email: armin.ronacher@active-4.com
License: UNKNOWN
Platform: UNKNOWN
Classifier: License :: OSI Approved :: BSD License
Classifier: Programming Language :: Python
